sans_fitter/__init__.py
sans_fitter/sans_fitter.py
sans_fitter-0.0.2.dist-info/licenses/LICENSE
sans_fitter-0.0.2.dist-info/METADATA
sans_fitter-0.0.2.dist-info/WHEEL
sans_fitter-0.0.2.dist-info/top_level.txt
sans_fitter-0.0.2.dist-info/RECORD
